haystack_lemmatize_node/__init__.py
haystack_lemmatize_node-0.0.2.dist-info/METADATA
haystack_lemmatize_node-0.0.2.dist-info/WHEEL
haystack_lemmatize_node-0.0.2.dist-info/licenses/LICENSE.md
haystack_lemmatize_node-0.0.2.dist-info/RECORD
