Metadata-Version: 2.1
Name: haystack_lemmatize_node
Version: 0.0.2
Summary: An Lemmatizing node for Deepset Haystack
Project-URL: Homepage, https://github.com/recrudesce/haystack_lemmatize_node
Project-URL: Bug Tracker, https://github.com/recrudesce/haystack_lemmatize_node/issues
Author-email: recrudesce <recrudesce@gmail.com>
License-File: LICENSE.md
Classifier: License :: OSI Approved :: MIT License
Classifier: Operating System :: OS Independent
Classifier: Programming Language :: Python :: 3
Requires-Python: >=3.10
Requires-Dist: farm-haystack
Requires-Dist: simplemma
